{
  "parent": "minecraft:recipes/root",
  "rewards": {
    "recipes": [
      "logical_crafting_recipes:oak_planks_from_oak_slabs"
    ]
  },
  "criteria": {
    "has_slabs": {
      "trigger": "minecraft:inventory_changed",
      "conditions": {
        "items": [
          {
            "item": "minecraft:oak_slab"
          }
        ]
      }
    },
    "has_the_recipe": {
      "trigger": "minecraft:recipe_unlocked",
      "conditions": {
        "recipe": "logical_crafting_recipes:oak_planks_from_oak_slabs"
      }
    }
  },
  "requirements": [
    [
      "has_slabs",
      "has_the_recipe"
    ]
  ]
}
